package com.cbs.app.cast;

import android.os.Handler;
import java.util.TimerTask;

final class CBSVideoCastControllerFragment$d
  extends TimerTask
{
  private CBSVideoCastControllerFragment$d(CBSVideoCastControllerFragment paramCBSVideoCastControllerFragment) {}
  
  public final void run()
  {
    CBSVideoCastControllerFragment.f(a).post(new Runnable()
    {
      /* Error */
      public final void run()
      {
        // Byte code:
        //   0: aload_0
        //   1: getfield 20	com/cbs/app/cast/CBSVideoCastControllerFragment$d$1:a	Lcom/cbs/app/cast/CBSVideoCastControllerFragment$d;
        //   4: getfield 32	com/cbs/app/cast/CBSVideoCastControllerFragment$d:a	Lcom/cbs/app/cast/CBSVideoCastControllerFragment;
        //   7: invokestatic 36	com/cbs/app/cast/CBSVideoCastControllerFragment:k	(Lcom/cbs/app/cast/CBSVideoCastControllerFragment;)I
        //   10: iconst_4
        //   11: if_icmpeq +19 -> 30
        //   14: aload_0
        //   15: getfield 20	com/cbs/app/cast/CBSVideoCastControllerFragment$d$1:a	Lcom/cbs/app/cast/CBSVideoCastControllerFragment$d;
        //   18: getfield 32	com/cbs/app/cast/CBSVideoCastControllerFragment$d:a	Lcom/cbs/app/cast/CBSVideoCastControllerFragment;
        //   21: invokestatic 40	com/cbs/app/cast/CBSVideoCastControllerFragment:g	(Lcom/cbs/app/cast/CBSVideoCastControllerFragment;)Lcom/google/android/libraries/cast/companionlibrary/cast/c;
        //   24: invokevirtual 46	com/google/android/libraries/cast/companionlibrary/cast/c:j	()Z
        //   27: ifne +4 -> 31
        //   30: return
        //   31: aload_0
        //   32: getfield 20	com/cbs/app/cast/CBSVideoCastControllerFragment$d$1:a	Lcom/cbs/app/cast/CBSVideoCastControllerFragment$d;
        //   35: getfield 32	com/cbs/app/cast/CBSVideoCastControllerFragment$d:a	Lcom/cbs/app/cast/CBSVideoCastControllerFragment;
        //   38: invokestatic 40	com/cbs/app/cast/CBSVideoCastControllerFragment:g	(Lcom/cbs/app/cast/CBSVideoCastControllerFragment;)Lcom/google/android/libraries/cast/companionlibrary/cast/c;
        //   41: invokevirtual 50	com/google/android/libraries/cast/companionlibrary/cast/c:M	()J
        //   44: lstore_3
        //   45: lload_3
        //   46: l2i
        //   47: istore_1
        //   48: iload_1
        //   49: ifle -19 -> 30
        //   52: aload_0
        //   53: getfield 20	com/cbs/app/cast/CBSVideoCastControllerFragment$d$1:a	Lcom/cbs/app/cast/CBSVideoCastControllerFragment$d;
        //   56: getfield 32	com/cbs/app/cast/CBSVideoCastControllerFragment$d:a	Lcom/cbs/app/cast/CBSVideoCastControllerFragment;
        //   59: invokestatic 40	com/cbs/app/cast/CBSVideoCastControllerFragment:g	(Lcom/cbs/app/cast/CBSVideoCastControllerFragment;)Lcom/google/android/libraries/cast/companionlibrary/cast/c;
        //   62: invokevirtual 53	com/google/android/libraries/cast/companionlibrary/cast/c:O	()J
        //   65: l2i
        //   66: istore_2
        //   67: aload_0
        //   68: getfield 20	com/cbs/app/cast/CBSVideoCastControllerFragment$d$1:a	Lcom/cbs/app/cast/CBSVideoCastControllerFragment$d;
        //   71: getfield 32	com/cbs/app/cast/CBSVideoCastControllerFragment$d:a	Lcom/cbs/app/cast/CBSVideoCastControllerFragment;
        //   74: invokestatic 57	com/cbs/app/cast/CBSVideoCastControllerFragment:b	(Lcom/cbs/app/cast/CBSVideoCastControllerFragment;)Lcom/google/android/libraries/cast/companionlibrary/cast/player/d;
        //   77: iload_2
        //   78: iload_1
        //   79: invokeinterface 62 3 0
        //   84: return
        //   85: astore 5
        //   87: ldc 64
        //   89: ldc 66
        //   91: aload 5
        //   93: invokestatic 71	com/google/android/libraries/cast/companionlibrary/a/b:a	(Ljava/lang/String;Ljava/lang/String;Ljava/lang/Throwable;)V
        //   96: return
        //   97: astore 5
        //   99: ldc 64
        //   101: ldc 73
        //   103: aload 5
        //   105: invokestatic 71	com/google/android/libraries/cast/companionlibrary/a/b:a	(Ljava/lang/String;Ljava/lang/String;Ljava/lang/Throwable;)V
        //   108: return
        //   109: astore 5
        //   111: goto -12 -> 99
        // Local variable table:
        //   start	length	slot	name	signature
        //   0	114	0	this	1
        //   47	32	1	i	int
        //   66	12	2	j	int
        //   44	2	3	l	long
        //   85	7	5	localException	Exception
        //   97	7	5	locald	com.google.android.libraries.cast.companionlibrary.cast.b.d
        //   109	1	5	localb	com.google.android.libraries.cast.companionlibrary.cast.b.b
        // Exception table:
        //   from	to	target	type
        //   52	84	85	java/lang/Exception
        //   31	45	97	com/google/android/libraries/cast/companionlibrary/cast/b/d
        //   52	84	97	com/google/android/libraries/cast/companionlibrary/cast/b/d
        //   87	96	97	com/google/android/libraries/cast/companionlibrary/cast/b/d
        //   31	45	109	com/google/android/libraries/cast/companionlibrary/cast/b/b
        //   52	84	109	com/google/android/libraries/cast/companionlibrary/cast/b/b
        //   87	96	109	com/google/android/libraries/cast/companionlibrary/cast/b/b
      }
    });
  }
}

/* Location:
 * Qualified Name:     com.cbs.app.cast.CBSVideoCastControllerFragment.d
 * Java Class Version: 6 (50.0)
 * JD-Core Version:    0.7.1
 */