package com.adobe.a.a;

import java.util.HashMap;

final class a$b
  implements Runnable
{
  public HashMap<String, Object> a;
  public a.a<HashMap> b;
  
  public a$b(HashMap<String, Object> paramHashMap, a.a<HashMap> parama)
  {
    a = paramHashMap;
    b = null;
  }
  
  /* Error */
  public final void run()
  {
    // Byte code:
    //   0: aconst_null
    //   1: astore_3
    //   2: aload_0
    //   3: getfield 21	com/adobe/a/a/a$b:a	Ljava/util/HashMap;
    //   6: invokestatic 32	com/adobe/a/a/a:b	(Ljava/util/HashMap;)Ljava/lang/String;
    //   9: astore_2
    //   10: ldc 34
    //   12: iconst_1
    //   13: anewarray 4	java/lang/Object
    //   16: dup
    //   17: iconst_0
    //   18: aload_2
    //   19: aastore
    //   20: invokestatic 37	com/adobe/a/a/a:a	(Ljava/lang/String;[Ljava/lang/Object;)V
    //   23: aload_2
    //   24: invokevirtual 43	java/lang/String:length	()I
    //   27: ifle +421 -> 448
    //   30: new 45	java/lang/StringBuilder
    //   33: dup
    //   34: invokespecial 46	java/lang/StringBuilder:<init>	()V
    //   37: astore 6
    //   39: new 48	org/apache/http/impl/client/DefaultHttpClient
    //   42: dup
    //   43: invokespecial 49	org/apache/http/impl/client/DefaultHttpClient:<init>	()V
    //   46: astore 5
    //   48: new 51	org/apache/http/client/methods/HttpGet
    //   51: dup
    //   52: aload_2
    //   53: invokespecial 54	org/apache/http/client/methods/HttpGet:<init>	(Ljava/lang/String;)V
    //   56: astore_2
    //   57: aload 5
    //   59: aload_2
    //   60: invokeinterface 60 2 0
    //   65: astore_2
    //   66: aload_2
    //   67: invokeinterface 66 1 0
    //   72: invokeinterface 71 1 0
    //   77: sipush 200
    //   80: if_icmpne +109 -> 189
    //   83: aload_2
    //   84: invokeinterface 75 1 0
    //   89: invokeinterface 81 1 0
    //   94: astore_2
    //   95: new 83	java/io/BufferedReader
    //   98: dup
    //   99: new 85	java/io/InputStreamReader
    //   102: dup
    //   103: aload_2
    //   104: ldc 87
    //   106: invokespecial 90	java/io/InputStreamReader:<init>	(Ljava/io/InputStream;Ljava/lang/String;)V
    //   109: invokespecial 93	java/io/BufferedReader:<init>	(Ljava/io/Reader;)V
    //   112: astore 4
    //   114: aload 4
    //   116: invokevirtual 97	java/io/BufferedReader:readLine	()Ljava/lang/String;
    //   119: astore_3
    //   120: aload_3
    //   121: ifnull +87 -> 208
    //   124: aload 6
    //   126: aload_3
    //   127: invokevirtual 101	java/lang/StringBuilder:append	(Ljava/lang/String;)Ljava/lang/StringBuilder;
    //   130: pop
    //   131: goto -17 -> 114
    //   134: astore 5
    //   136: aload_2
    //   137: astore_3
    //   138: aload 4
    //   140: astore_2
    //   141: aload 5
    //   143: astore 4
    //   145: ldc 103
    //   147: iconst_1
    //   148: anewarray 4	java/lang/Object
    //   151: dup
    //   152: iconst_0
    //   153: aload 4
    //   155: invokevirtual 106	java/lang/Exception:getLocalizedMessage	()Ljava/lang/String;
    //   158: aastore
    //   159: invokestatic 108	com/adobe/a/a/a:b	(Ljava/lang/String;[Ljava/lang/Object;)V
    //   162: aload_3
    //   163: invokevirtual 113	java/io/InputStream:close	()V
    //   166: aload_2
    //   167: invokevirtual 114	java/io/BufferedReader:close	()V
    //   170: return
    //   171: astore_2
    //   172: ldc 116
    //   174: iconst_1
    //   175: anewarray 4	java/lang/Object
    //   178: dup
    //   179: iconst_0
    //   180: aload_2
    //   181: invokevirtual 106	java/lang/Exception:getLocalizedMessage	()Ljava/lang/String;
    //   184: aastore
    //   185: invokestatic 108	com/adobe/a/a/a:b	(Ljava/lang/String;[Ljava/lang/Object;)V
    //   188: return
    //   189: ldc 118
    //   191: iconst_0
    //   192: anewarray 4	java/lang/Object
    //   195: invokestatic 108	com/adobe/a/a/a:b	(Ljava/lang/String;[Ljava/lang/Object;)V
    //   198: new 120	java/lang/NullPointerException
    //   201: dup
    //   202: invokespecial 121	java/lang/NullPointerException:<init>	()V
    //   205: athrow
    //   206: astore_2
    //   207: return
    //   208: new 123	org/json/JSONObject
    //   211: dup
    //   212: aload 6
    //   214: invokevirtual 126	java/lang/StringBuilder:toString	()Ljava/lang/String;
    //   217: invokespecial 127	org/json/JSONObject:<init>	(Ljava/lang/String;)V
    //   220: astore_3
    //   221: aload_3
    //   222: ldc -127
    //   224: invokevirtual 133	org/json/JSONObject:getJSONArray	(Ljava/lang/String;)Lorg/json/JSONArray;
    //   227: astore 7
    //   229: iconst_0
    //   230: istore_1
    //   231: iload_1
    //   232: aload 7
    //   234: invokevirtual 136	org/json/JSONArray:length	()I
    //   237: if_icmpge +110 -> 347
    //   240: aload 7
    //   242: iload_1
    //   243: invokevirtual 140	org/json/JSONArray:getJSONObject	(I)Lorg/json/JSONObject;
    //   246: ldc -114
    //   248: invokevirtual 146	org/json/JSONObject:getString	(Ljava/lang/String;)Ljava/lang/String;
    //   251: astore 6
    //   253: ldc -108
    //   255: iconst_1
    //   256: anewarray 4	java/lang/Object
    //   259: dup
    //   260: iconst_0
    //   261: aload 6
    //   263: aastore
    //   264: invokestatic 37	com/adobe/a/a/a:a	(Ljava/lang/String;[Ljava/lang/Object;)V
    //   267: aload 6
    //   269: ifnull +32 -> 301
    //   272: aload 6
    //   274: invokevirtual 43	java/lang/String:length	()I
    //   277: ifle +24 -> 301
    //   280: new 51	org/apache/http/client/methods/HttpGet
    //   283: dup
    //   284: aload 6
    //   286: invokespecial 54	org/apache/http/client/methods/HttpGet:<init>	(Ljava/lang/String;)V
    //   289: astore 8
    //   291: aload 5
    //   293: aload 8
    //   295: invokeinterface 60 2 0
    //   300: pop
    //   301: iload_1
    //   302: iconst_1
    //   303: iadd
    //   304: istore_1
    //   305: goto -74 -> 231
    //   308: astore 8
    //   310: ldc -106
    //   312: iconst_2
    //   313: anewarray 4	java/lang/Object
    //   316: dup
    //   317: iconst_0
    //   318: aload 6
    //   320: aastore
    //   321: dup
    //   322: iconst_1
    //   323: aload 8
    //   325: invokevirtual 106	java/lang/Exception:getLocalizedMessage	()Ljava/lang/String;
    //   328: aastore
    //   329: invokestatic 108	com/adobe/a/a/a:b	(Ljava/lang/String;[Ljava/lang/Object;)V
    //   332: goto -31 -> 301
    //   335: astore_3
    //   336: aload_2
    //   337: invokevirtual 113	java/io/InputStream:close	()V
    //   340: aload 4
    //   342: invokevirtual 114	java/io/BufferedReader:close	()V
    //   345: aload_3
    //   346: athrow
    //   347: aload_3
    //   348: ldc -104
    //   350: invokevirtual 146	org/json/JSONObject:getString	(Ljava/lang/String;)Ljava/lang/String;
    //   353: invokestatic 154	com/adobe/a/a/a:a	(Ljava/lang/String;)V
    //   356: aload_3
    //   357: ldc -100
    //   359: invokevirtual 133	org/json/JSONObject:getJSONArray	(Ljava/lang/String;)Lorg/json/JSONArray;
    //   362: astore_3
    //   363: new 158	java/util/HashMap
    //   366: dup
    //   367: invokespecial 159	java/util/HashMap:<init>	()V
    //   370: astore 6
    //   372: iconst_0
    //   373: istore_1
    //   374: iload_1
    //   375: aload_3
    //   376: invokevirtual 136	org/json/JSONArray:length	()I
    //   379: if_icmpge +38 -> 417
    //   382: aload_3
    //   383: iload_1
    //   384: invokevirtual 140	org/json/JSONArray:getJSONObject	(I)Lorg/json/JSONObject;
    //   387: astore 5
    //   389: aload 5
    //   391: ifnull +126 -> 517
    //   394: aload 6
    //   396: aload 5
    //   398: ldc -95
    //   400: invokevirtual 146	org/json/JSONObject:getString	(Ljava/lang/String;)Ljava/lang/String;
    //   403: aload 5
    //   405: ldc -93
    //   407: invokevirtual 146	org/json/JSONObject:getString	(Ljava/lang/String;)Ljava/lang/String;
    //   410: invokevirtual 167	java/util/HashMap:put	(Ljava/lang/Object;Ljava/lang/Object;)Ljava/lang/Object;
    //   413: pop
    //   414: goto +103 -> 517
    //   417: ldc -87
    //   419: iconst_1
    //   420: anewarray 4	java/lang/Object
    //   423: dup
    //   424: iconst_0
    //   425: aload 6
    //   427: aastore
    //   428: invokestatic 37	com/adobe/a/a/a:a	(Ljava/lang/String;[Ljava/lang/Object;)V
    //   431: aload 6
    //   433: invokestatic 172	com/adobe/a/a/a:c	(Ljava/util/HashMap;)V
    //   436: aload_2
    //   437: invokevirtual 113	java/io/InputStream:close	()V
    //   440: aload 4
    //   442: invokevirtual 114	java/io/BufferedReader:close	()V
    //   445: return
    //   446: astore_2
    //   447: return
    //   448: ldc -82
    //   450: iconst_0
    //   451: anewarray 4	java/lang/Object
    //   454: invokestatic 108	com/adobe/a/a/a:b	(Ljava/lang/String;[Ljava/lang/Object;)V
    //   457: return
    //   458: astore_2
    //   459: goto -114 -> 345
    //   462: astore_3
    //   463: aconst_null
    //   464: astore 4
    //   466: aconst_null
    //   467: astore_2
    //   468: goto -132 -> 336
    //   471: astore_3
    //   472: aconst_null
    //   473: astore 4
    //   475: goto -139 -> 336
    //   478: astore 4
    //   480: aload_3
    //   481: astore 5
    //   483: aload 4
    //   485: astore_3
    //   486: aload_2
    //   487: astore 4
    //   489: aload 5
    //   491: astore_2
    //   492: goto -156 -> 336
    //   495: astore_2
    //   496: return
    //   497: astore 4
    //   499: aconst_null
    //   500: astore_2
    //   501: goto -356 -> 145
    //   504: astore 4
    //   506: aconst_null
    //   507: astore 5
    //   509: aload_2
    //   510: astore_3
    //   511: aload 5
    //   513: astore_2
    //   514: goto -369 -> 145
    //   517: iload_1
    //   518: iconst_1
    //   519: iadd
    //   520: istore_1
    //   521: goto -147 -> 374
    // Local variable table:
    //   start	length	slot	name	signature
    //   0	524	0	this	b
    //   230	291	1	i	int
    //   9	158	2	localObject1	Object
    //   171	10	2	localException1	Exception
    //   206	231	2	localException2	Exception
    //   446	1	2	localException3	Exception
    //   458	1	2	localException4	Exception
    //   467	25	2	localObject2	Object
    //   495	1	2	localException5	Exception
    //   500	14	2	localObject3	Object
    //   1	221	3	localObject4	Object
    //   335	22	3	localObject5	Object
    //   362	21	3	localJSONArray1	org.json.JSONArray
    //   462	1	3	localObject6	Object
    //   471	10	3	localObject7	Object
    //   485	26	3	localObject8	Object
    //   112	362	4	localObject9	Object
    //   478	6	4	localObject10	Object
    //   487	1	4	localObject11	Object
    //   497	1	4	localException6	Exception
    //   504	1	4	localException7	Exception
    //   46	12	5	localDefaultHttpClient	org.apache.http.impl.client.DefaultHttpClient
    //   134	158	5	localException8	Exception
    //   387	125	5	localObject12	Object
    //   37	395	6	localObject13	Object
    //   227	14	7	localJSONArray2	org.json.JSONArray
    //   289	5	8	localHttpGet	org.apache.http.client.methods.HttpGet
    //   308	16	8	localException9	Exception
    // Exception table:
    //   from	to	target	type
    //   114	120	134	java/lang/Exception
    //   124	131	134	java/lang/Exception
    //   208	229	134	java/lang/Exception
    //   231	267	134	java/lang/Exception
    //   272	291	134	java/lang/Exception
    //   310	332	134	java/lang/Exception
    //   347	372	134	java/lang/Exception
    //   374	389	134	java/lang/Exception
    //   394	414	134	java/lang/Exception
    //   417	436	134	java/lang/Exception
    //   48	57	171	java/lang/Exception
    //   198	206	206	java/lang/Exception
    //   291	301	308	java/lang/Exception
    //   114	120	335	finally
    //   124	131	335	finally
    //   208	229	335	finally
    //   231	267	335	finally
    //   272	291	335	finally
    //   291	301	335	finally
    //   310	332	335	finally
    //   347	372	335	finally
    //   374	389	335	finally
    //   394	414	335	finally
    //   417	436	335	finally
    //   436	445	446	java/lang/Exception
    //   336	345	458	java/lang/Exception
    //   57	95	462	finally
    //   189	198	462	finally
    //   95	114	471	finally
    //   145	162	478	finally
    //   162	170	495	java/lang/Exception
    //   57	95	497	java/lang/Exception
    //   189	198	497	java/lang/Exception
    //   95	114	504	java/lang/Exception
  }
}

/* Location:
 * Qualified Name:     com.adobe.a.a.a.b
 * Java Class Version: 6 (50.0)
 * JD-Core Version:    0.7.1
 */