package com.conviva.utils;

class Utils$1
  implements CallableWithParameters.With1<String>
{
  Utils$1(Utils paramUtils) {}
  
  /* Error */
  public void exec(String paramString)
  {
    // Byte code:
    //   0: aconst_null
    //   1: astore_2
    //   2: invokestatic 36	com/conviva/utils/Utils:access$000	()Landroid/content/Context;
    //   5: ldc 38
    //   7: iconst_0
    //   8: invokevirtual 44	android/content/Context:openFileOutput	(Ljava/lang/String;I)Ljava/io/FileOutputStream;
    //   11: astore 4
    //   13: aload 4
    //   15: astore_2
    //   16: aload 4
    //   18: astore_3
    //   19: aload 4
    //   21: aload_1
    //   22: invokevirtual 48	java/lang/String:getBytes	()[B
    //   25: invokevirtual 54	java/io/FileOutputStream:write	([B)V
    //   28: aload 4
    //   30: astore_2
    //   31: aload 4
    //   33: astore_3
    //   34: aload 4
    //   36: invokevirtual 57	java/io/FileOutputStream:flush	()V
    //   39: aload 4
    //   41: astore_2
    //   42: aload 4
    //   44: astore_3
    //   45: aload 4
    //   47: invokevirtual 60	java/io/FileOutputStream:close	()V
    //   50: aload 4
    //   52: ifnull +8 -> 60
    //   55: aload 4
    //   57: invokevirtual 60	java/io/FileOutputStream:close	()V
    //   60: return
    //   61: astore_1
    //   62: aload_1
    //   63: invokevirtual 63	java/io/IOException:printStackTrace	()V
    //   66: return
    //   67: astore_1
    //   68: aload_2
    //   69: astore_3
    //   70: aload_0
    //   71: getfield 18	com/conviva/utils/Utils$1:this$0	Lcom/conviva/utils/Utils;
    //   74: ldc 65
    //   76: invokevirtual 68	com/conviva/utils/Utils:log	(Ljava/lang/String;)V
    //   79: aload_2
    //   80: ifnull -20 -> 60
    //   83: aload_2
    //   84: invokevirtual 60	java/io/FileOutputStream:close	()V
    //   87: return
    //   88: astore_1
    //   89: aload_1
    //   90: invokevirtual 63	java/io/IOException:printStackTrace	()V
    //   93: return
    //   94: astore_1
    //   95: aconst_null
    //   96: astore_3
    //   97: aload_3
    //   98: ifnull +7 -> 105
    //   101: aload_3
    //   102: invokevirtual 60	java/io/FileOutputStream:close	()V
    //   105: aload_1
    //   106: athrow
    //   107: astore_2
    //   108: aload_2
    //   109: invokevirtual 63	java/io/IOException:printStackTrace	()V
    //   112: goto -7 -> 105
    //   115: astore_1
    //   116: goto -19 -> 97
    // Local variable table:
    //   start	length	slot	name	signature
    //   0	119	0	this	1
    //   0	119	1	paramString	String
    //   1	83	2	localObject1	Object
    //   107	2	2	localIOException	java.io.IOException
    //   18	84	3	localObject2	Object
    //   11	45	4	localFileOutputStream	java.io.FileOutputStream
    // Exception table:
    //   from	to	target	type
    //   55	60	61	java/io/IOException
    //   2	13	67	java/lang/Exception
    //   19	28	67	java/lang/Exception
    //   34	39	67	java/lang/Exception
    //   45	50	67	java/lang/Exception
    //   83	87	88	java/io/IOException
    //   2	13	94	finally
    //   101	105	107	java/io/IOException
    //   19	28	115	finally
    //   34	39	115	finally
    //   45	50	115	finally
    //   70	79	115	finally
  }
}

/* Location:
 * Qualified Name:     com.conviva.utils.Utils.1
 * Java Class Version: 6 (50.0)
 * JD-Core Version:    0.7.1
 */