package com.conviva.utils;

class Utils$1LoadDataTask
  implements Runnable
{
  Utils$1LoadDataTask(Utils paramUtils) {}
  
  /* Error */
  public void run()
  {
    // Byte code:
    //   0: aconst_null
    //   1: astore_3
    //   2: aconst_null
    //   3: astore 5
    //   5: invokestatic 28	com/conviva/utils/Utils:access$000	()Landroid/content/Context;
    //   8: ldc 30
    //   10: invokevirtual 36	android/content/Context:getFileStreamPath	(Ljava/lang/String;)Ljava/io/File;
    //   13: invokevirtual 42	java/io/File:exists	()Z
    //   16: ifeq +293 -> 309
    //   19: new 44	java/lang/StringBuffer
    //   22: dup
    //   23: ldc 46
    //   25: invokespecial 49	java/lang/StringBuffer:<init>	(Ljava/lang/String;)V
    //   28: astore 4
    //   30: invokestatic 28	com/conviva/utils/Utils:access$000	()Landroid/content/Context;
    //   33: ldc 30
    //   35: invokevirtual 53	android/content/Context:openFileInput	(Ljava/lang/String;)Ljava/io/FileInputStream;
    //   38: astore_2
    //   39: aload_2
    //   40: astore_3
    //   41: aload_3
    //   42: astore_2
    //   43: sipush 1024
    //   46: newarray <illegal type>
    //   48: astore 6
    //   50: aload_3
    //   51: astore_2
    //   52: aload_3
    //   53: aload 6
    //   55: invokevirtual 59	java/io/FileInputStream:read	([B)I
    //   58: istore_1
    //   59: iload_1
    //   60: iconst_m1
    //   61: if_icmpeq +146 -> 207
    //   64: aload_3
    //   65: astore_2
    //   66: aload 4
    //   68: new 61	java/lang/String
    //   71: dup
    //   72: aload 6
    //   74: iconst_0
    //   75: iload_1
    //   76: invokespecial 64	java/lang/String:<init>	([BII)V
    //   79: invokevirtual 68	java/lang/StringBuffer:append	(Ljava/lang/String;)Ljava/lang/StringBuffer;
    //   82: pop
    //   83: goto -33 -> 50
    //   86: astore_2
    //   87: aload_3
    //   88: astore_2
    //   89: aload_0
    //   90: getfield 15	com/conviva/utils/Utils$1LoadDataTask:this$0	Lcom/conviva/utils/Utils;
    //   93: ldc 70
    //   95: invokevirtual 73	com/conviva/utils/Utils:err	(Ljava/lang/String;)V
    //   98: aload_3
    //   99: ifnull +7 -> 106
    //   102: aload_3
    //   103: invokevirtual 76	java/io/FileInputStream:close	()V
    //   106: aconst_null
    //   107: astore_2
    //   108: aload 5
    //   110: astore_3
    //   111: aload_2
    //   112: ifnull +29 -> 141
    //   115: aload 5
    //   117: astore_3
    //   118: aload_2
    //   119: ldc 78
    //   121: invokeinterface 84 2 0
    //   126: ifeq +15 -> 141
    //   129: aload_2
    //   130: ldc 78
    //   132: invokeinterface 88 2 0
    //   137: invokevirtual 92	java/lang/Object:toString	()Ljava/lang/String;
    //   140: astore_3
    //   141: aload_3
    //   142: ifnull +141 -> 283
    //   145: aload_3
    //   146: ldc 94
    //   148: invokevirtual 97	java/lang/String:equals	(Ljava/lang/Object;)Z
    //   151: ifne +132 -> 283
    //   154: aload_3
    //   155: ldc 99
    //   157: invokevirtual 97	java/lang/String:equals	(Ljava/lang/Object;)Z
    //   160: ifne +123 -> 283
    //   163: aload_3
    //   164: invokevirtual 103	java/lang/String:length	()I
    //   167: ifle +116 -> 283
    //   170: aload_0
    //   171: getfield 15	com/conviva/utils/Utils$1LoadDataTask:this$0	Lcom/conviva/utils/Utils;
    //   174: aload_3
    //   175: putfield 107	com/conviva/utils/Utils:clientId	Ljava/lang/String;
    //   178: aload_0
    //   179: getfield 15	com/conviva/utils/Utils$1LoadDataTask:this$0	Lcom/conviva/utils/Utils;
    //   182: new 109	java/lang/StringBuilder
    //   185: dup
    //   186: ldc 111
    //   188: invokespecial 112	java/lang/StringBuilder:<init>	(Ljava/lang/String;)V
    //   191: aload_3
    //   192: invokevirtual 115	java/lang/StringBuilder:append	(Ljava/lang/String;)Ljava/lang/StringBuilder;
    //   195: ldc 117
    //   197: invokevirtual 115	java/lang/StringBuilder:append	(Ljava/lang/String;)Ljava/lang/StringBuilder;
    //   200: invokevirtual 118	java/lang/StringBuilder:toString	()Ljava/lang/String;
    //   203: invokevirtual 121	com/conviva/utils/Utils:log	(Ljava/lang/String;)V
    //   206: return
    //   207: aload_3
    //   208: astore_2
    //   209: aload_3
    //   210: invokevirtual 76	java/io/FileInputStream:close	()V
    //   213: aload_3
    //   214: astore_2
    //   215: aload_0
    //   216: getfield 15	com/conviva/utils/Utils$1LoadDataTask:this$0	Lcom/conviva/utils/Utils;
    //   219: aload 4
    //   221: invokevirtual 122	java/lang/StringBuffer:toString	()Ljava/lang/String;
    //   224: invokevirtual 126	com/conviva/utils/Utils:jsonDecode	(Ljava/lang/String;)Ljava/util/Map;
    //   227: astore 4
    //   229: aload_3
    //   230: ifnull +7 -> 237
    //   233: aload_3
    //   234: invokevirtual 76	java/io/FileInputStream:close	()V
    //   237: aload 4
    //   239: astore_2
    //   240: goto -132 -> 108
    //   243: astore_2
    //   244: aload_2
    //   245: invokevirtual 129	java/io/IOException:printStackTrace	()V
    //   248: aload 4
    //   250: astore_2
    //   251: goto -143 -> 108
    //   254: astore_2
    //   255: aload_2
    //   256: invokevirtual 129	java/io/IOException:printStackTrace	()V
    //   259: aconst_null
    //   260: astore_2
    //   261: goto -153 -> 108
    //   264: astore_2
    //   265: aload_3
    //   266: ifnull +7 -> 273
    //   269: aload_3
    //   270: invokevirtual 76	java/io/FileInputStream:close	()V
    //   273: aload_2
    //   274: athrow
    //   275: astore_3
    //   276: aload_3
    //   277: invokevirtual 129	java/io/IOException:printStackTrace	()V
    //   280: goto -7 -> 273
    //   283: aload_0
    //   284: getfield 15	com/conviva/utils/Utils$1LoadDataTask:this$0	Lcom/conviva/utils/Utils;
    //   287: ldc -125
    //   289: invokevirtual 121	com/conviva/utils/Utils:log	(Ljava/lang/String;)V
    //   292: return
    //   293: astore 4
    //   295: aload_2
    //   296: astore_3
    //   297: aload 4
    //   299: astore_2
    //   300: goto -35 -> 265
    //   303: astore_2
    //   304: aconst_null
    //   305: astore_3
    //   306: goto -219 -> 87
    //   309: aconst_null
    //   310: astore_2
    //   311: goto -203 -> 108
    // Local variable table:
    //   start	length	slot	name	signature
    //   0	314	0	this	1LoadDataTask
    //   58	18	1	i	int
    //   38	28	2	localObject1	Object
    //   86	1	2	localException1	Exception
    //   88	152	2	localObject2	Object
    //   243	2	2	localIOException1	java.io.IOException
    //   250	1	2	localObject3	Object
    //   254	2	2	localIOException2	java.io.IOException
    //   260	1	2	localObject4	Object
    //   264	32	2	localObject5	Object
    //   299	1	2	localObject6	Object
    //   303	1	2	localException2	Exception
    //   310	1	2	localObject7	Object
    //   1	269	3	localObject8	Object
    //   275	2	3	localIOException3	java.io.IOException
    //   296	10	3	localObject9	Object
    //   28	221	4	localObject10	Object
    //   293	5	4	localObject11	Object
    //   3	113	5	localObject12	Object
    //   48	25	6	arrayOfByte	byte[]
    // Exception table:
    //   from	to	target	type
    //   43	50	86	java/lang/Exception
    //   52	59	86	java/lang/Exception
    //   66	83	86	java/lang/Exception
    //   209	213	86	java/lang/Exception
    //   215	229	86	java/lang/Exception
    //   233	237	243	java/io/IOException
    //   102	106	254	java/io/IOException
    //   30	39	264	finally
    //   269	273	275	java/io/IOException
    //   43	50	293	finally
    //   52	59	293	finally
    //   66	83	293	finally
    //   89	98	293	finally
    //   209	213	293	finally
    //   215	229	293	finally
    //   30	39	303	java/lang/Exception
  }
}

/* Location:
 * Qualified Name:     com.conviva.utils.Utils.1LoadDataTask
 * Java Class Version: 6 (50.0)
 * JD-Core Version:    0.7.1
 */