package com.cbs.app.uri;

import android.content.Context;
import android.os.AsyncTask;

public class UriHandler$GetShowIdAsyncTask
  extends AsyncTask<String, Void, Long>
{
  private Context a = null;
  
  public UriHandler$GetShowIdAsyncTask(Context paramContext)
  {
    a = paramContext;
  }
  
  /* Error */
  private Long a(String... arg1)
  {
    // Byte code:
    //   0: aconst_null
    //   1: astore 5
    //   3: aconst_null
    //   4: astore 6
    //   6: aload_0
    //   7: getfield 17	com/cbs/app/uri/UriHandler$GetShowIdAsyncTask:a	Landroid/content/Context;
    //   10: ifnull +311 -> 321
    //   13: aload_1
    //   14: ifnull +307 -> 321
    //   17: aload_1
    //   18: arraylength
    //   19: ifle +302 -> 321
    //   22: aload_1
    //   23: iconst_0
    //   24: aaload
    //   25: astore_1
    //   26: aload_0
    //   27: getfield 17	com/cbs/app/uri/UriHandler$GetShowIdAsyncTask:a	Landroid/content/Context;
    //   30: invokestatic 31	com/cbs/app/view/utils/Util:B	(Landroid/content/Context;)Ljava/lang/String;
    //   33: astore 7
    //   35: aload 7
    //   37: ifnull +284 -> 321
    //   40: new 33	java/net/URL
    //   43: dup
    //   44: aload 7
    //   46: invokespecial 36	java/net/URL:<init>	(Ljava/lang/String;)V
    //   49: invokevirtual 40	java/net/URL:getHost	()Ljava/lang/String;
    //   52: astore 7
    //   54: new 33	java/net/URL
    //   57: dup
    //   58: new 42	java/lang/StringBuilder
    //   61: dup
    //   62: ldc 44
    //   64: invokespecial 45	java/lang/StringBuilder:<init>	(Ljava/lang/String;)V
    //   67: aload 7
    //   69: invokevirtual 49	java/lang/StringBuilder:append	(Ljava/lang/String;)Ljava/lang/StringBuilder;
    //   72: ldc 51
    //   74: invokevirtual 49	java/lang/StringBuilder:append	(Ljava/lang/String;)Ljava/lang/StringBuilder;
    //   77: aload_1
    //   78: invokevirtual 49	java/lang/StringBuilder:append	(Ljava/lang/String;)Ljava/lang/StringBuilder;
    //   81: ldc 53
    //   83: invokevirtual 49	java/lang/StringBuilder:append	(Ljava/lang/String;)Ljava/lang/StringBuilder;
    //   86: invokevirtual 56	java/lang/StringBuilder:toString	()Ljava/lang/String;
    //   89: invokespecial 36	java/net/URL:<init>	(Ljava/lang/String;)V
    //   92: invokevirtual 60	java/net/URL:openConnection	()Ljava/net/URLConnection;
    //   95: checkcast 62	java/net/HttpURLConnection
    //   98: astore_1
    //   99: aload_1
    //   100: sipush 5000
    //   103: invokevirtual 66	java/net/HttpURLConnection:setReadTimeout	(I)V
    //   106: aload_1
    //   107: sipush 5000
    //   110: invokevirtual 69	java/net/HttpURLConnection:setConnectTimeout	(I)V
    //   113: aload 6
    //   115: astore 5
    //   117: aload_1
    //   118: invokevirtual 73	java/net/HttpURLConnection:getResponseCode	()I
    //   121: sipush 200
    //   124: if_icmpne +118 -> 242
    //   127: new 75	java/io/BufferedReader
    //   130: dup
    //   131: new 77	java/io/InputStreamReader
    //   134: dup
    //   135: aload_1
    //   136: invokevirtual 81	java/net/HttpURLConnection:getInputStream	()Ljava/io/InputStream;
    //   139: ldc 83
    //   141: invokespecial 86	java/io/InputStreamReader:<init>	(Ljava/io/InputStream;Ljava/lang/String;)V
    //   144: invokespecial 89	java/io/BufferedReader:<init>	(Ljava/io/Reader;)V
    //   147: astore 5
    //   149: new 42	java/lang/StringBuilder
    //   152: dup
    //   153: invokespecial 90	java/lang/StringBuilder:<init>	()V
    //   156: astore 7
    //   158: aload 5
    //   160: invokevirtual 93	java/io/BufferedReader:readLine	()Ljava/lang/String;
    //   163: astore 8
    //   165: aload 8
    //   167: ifnull +26 -> 193
    //   170: aload 7
    //   172: aload 8
    //   174: invokevirtual 49	java/lang/StringBuilder:append	(Ljava/lang/String;)Ljava/lang/StringBuilder;
    //   177: pop
    //   178: goto -20 -> 158
    //   181: astore 5
    //   183: aload_1
    //   184: ifnull +137 -> 321
    //   187: aload_1
    //   188: invokevirtual 96	java/net/HttpURLConnection:disconnect	()V
    //   191: aconst_null
    //   192: areturn
    //   193: aload 5
    //   195: invokevirtual 99	java/io/BufferedReader:close	()V
    //   198: new 101	org/json/JSONObject
    //   201: dup
    //   202: aload 7
    //   204: invokevirtual 56	java/lang/StringBuilder:toString	()Ljava/lang/String;
    //   207: invokespecial 102	org/json/JSONObject:<init>	(Ljava/lang/String;)V
    //   210: astore 5
    //   212: aload 5
    //   214: ldc 104
    //   216: invokevirtual 108	org/json/JSONObject:getBoolean	(Ljava/lang/String;)Z
    //   219: istore_2
    //   220: aload 5
    //   222: ldc 110
    //   224: invokevirtual 114	org/json/JSONObject:getLong	(Ljava/lang/String;)J
    //   227: lstore_3
    //   228: aload 6
    //   230: astore 5
    //   232: iload_2
    //   233: ifeq +9 -> 242
    //   236: lload_3
    //   237: invokestatic 120	java/lang/Long:valueOf	(J)Ljava/lang/Long;
    //   240: astore 5
    //   242: aload_1
    //   243: ifnull +80 -> 323
    //   246: aload_1
    //   247: invokevirtual 96	java/net/HttpURLConnection:disconnect	()V
    //   250: aload 5
    //   252: areturn
    //   253: astore_1
    //   254: aload_1
    //   255: invokevirtual 125	java/lang/NumberFormatException:printStackTrace	()V
    //   258: goto -16 -> 242
    //   261: astore 5
    //   263: aload 5
    //   265: invokevirtual 126	org/json/JSONException:printStackTrace	()V
    //   268: aload 6
    //   270: astore 5
    //   272: goto -30 -> 242
    //   275: astore 5
    //   277: aload_1
    //   278: astore 6
    //   280: aload 5
    //   282: astore_1
    //   283: aload 6
    //   285: ifnull +8 -> 293
    //   288: aload 6
    //   290: invokevirtual 96	java/net/HttpURLConnection:disconnect	()V
    //   293: aload_1
    //   294: athrow
    //   295: astore_1
    //   296: aload 5
    //   298: areturn
    //   299: astore_1
    //   300: aconst_null
    //   301: areturn
    //   302: astore 5
    //   304: goto -11 -> 293
    //   307: astore_1
    //   308: aload 5
    //   310: astore 6
    //   312: goto -29 -> 283
    //   315: astore_1
    //   316: aconst_null
    //   317: astore_1
    //   318: goto -135 -> 183
    //   321: aconst_null
    //   322: areturn
    //   323: aload 5
    //   325: areturn
    // Exception table:
    //   from	to	target	type
    //   99	113	181	java/io/IOException
    //   117	158	181	java/io/IOException
    //   158	165	181	java/io/IOException
    //   170	178	181	java/io/IOException
    //   193	198	181	java/io/IOException
    //   198	228	181	java/io/IOException
    //   254	258	181	java/io/IOException
    //   263	268	181	java/io/IOException
    //   198	228	261	org/json/JSONException
    //   254	258	261	org/json/JSONException
    //   99	113	275	finally
    //   117	158	275	finally
    //   158	165	275	finally
    //   170	178	275	finally
    //   193	198	275	finally
    //   198	228	275	finally
    //   254	258	275	finally
    //   263	268	275	finally
    //   246	250	295	java/lang/Exception
    //   187	191	299	java/lang/Exception
    //   288	293	302	java/lang/Exception
    //   40	99	307	finally
    //   40	99	315	java/io/IOException
  }
}

/* Location:
 * Qualified Name:     com.cbs.app.uri.UriHandler.GetShowIdAsyncTask
 * Java Class Version: 6 (50.0)
 * JD-Core Version:    0.7.1
 */