package com.adobe.mobile;

import java.io.IOException;
import java.io.InputStream;
import java.net.HttpURLConnection;
import java.net.SocketTimeoutException;
import java.net.URL;
import javax.net.ssl.HttpsURLConnection;
import org.apache.http.conn.ssl.StrictHostnameVerifier;

final class al
{
  private static final Object a = new Object();
  private static StrictHostnameVerifier b = null;
  
  private static HttpURLConnection a(String arg0)
  {
    try
    {
      URL localURL = new URL(???);
      if (localURL.getProtocol().equals("https")) {
        synchronized (a)
        {
          if (b == null) {
            b = new StrictHostnameVerifier();
          }
          ??? = (HttpsURLConnection)localURL.openConnection();
          ???.setHostnameVerifier(b);
          return (HttpURLConnection)???;
        }
      }
      ??? = (HttpURLConnection)((URL)localObject).openConnection();
    }
    catch (Exception ???)
    {
      am.a("Adobe Mobile - Exception opening URL(%s)", new Object[] { ???.getLocalizedMessage() });
      return null;
    }
    return (HttpURLConnection)???;
  }
  
  protected static void a(String paramString1, String paramString2)
  {
    if (paramString1 == null) {}
    for (;;)
    {
      return;
      if (am.o())
      {
        ap.a(paramString1, null, 5000, paramString2);
        return;
      }
      try
      {
        HttpURLConnection localHttpURLConnection = a(paramString1);
        if (localHttpURLConnection != null)
        {
          localHttpURLConnection.setConnectTimeout(5000);
          localHttpURLConnection.setReadTimeout(5000);
          am.c("%s - Request Sent(%s)", new Object[] { paramString2, paramString1 });
          localHttpURLConnection.getResponseCode();
          localHttpURLConnection.getInputStream().close();
          localHttpURLConnection.disconnect();
          return;
        }
      }
      catch (SocketTimeoutException localSocketTimeoutException)
      {
        am.b("%s - Timed out sending request(%s)", new Object[] { paramString2, paramString1 });
        return;
      }
      catch (IOException paramString1)
      {
        am.b("%s - IOException while sending request, may retry(%s)", new Object[] { paramString2, paramString1.getLocalizedMessage() });
        return;
      }
      catch (Exception paramString1)
      {
        am.b("%s - Exception while attempting to send hit, will not retry(%s)", new Object[] { paramString2, paramString1.getLocalizedMessage() });
        return;
      }
      catch (Error paramString1)
      {
        am.b("%s - Exception while attempting to send hit, will not retry(%s)", new Object[] { paramString2, paramString1.getLocalizedMessage() });
      }
    }
  }
  
  /* Error */
  protected static boolean a(String paramString1, String paramString2, java.util.Map<String, String> paramMap)
  {
    // Byte code:
    //   0: aload_0
    //   1: ifnonnull +5 -> 6
    //   4: iconst_0
    //   5: ireturn
    //   6: invokestatic 74	com/adobe/mobile/am:o	()Z
    //   9: ifeq +13 -> 22
    //   12: aload_0
    //   13: aload_1
    //   14: aload_2
    //   15: sipush 5000
    //   18: invokestatic 124	com/adobe/mobile/ap:a	(Ljava/lang/String;Ljava/lang/String;Ljava/util/Map;I)Z
    //   21: ireturn
    //   22: aload_0
    //   23: invokestatic 81	com/adobe/mobile/al:a	(Ljava/lang/String;)Ljava/net/HttpURLConnection;
    //   26: astore_0
    //   27: aload_0
    //   28: ifnonnull +5 -> 33
    //   31: iconst_0
    //   32: ireturn
    //   33: aload_0
    //   34: sipush 5000
    //   37: invokevirtual 85	java/net/HttpURLConnection:setConnectTimeout	(I)V
    //   40: aload_0
    //   41: sipush 5000
    //   44: invokevirtual 88	java/net/HttpURLConnection:setReadTimeout	(I)V
    //   47: aload_0
    //   48: ldc 126
    //   50: invokevirtual 129	java/net/HttpURLConnection:setRequestMethod	(Ljava/lang/String;)V
    //   53: aload_1
    //   54: ldc -125
    //   56: invokevirtual 135	java/lang/String:getBytes	(Ljava/lang/String;)[B
    //   59: astore_3
    //   60: aload_0
    //   61: aload_3
    //   62: arraylength
    //   63: invokevirtual 138	java/net/HttpURLConnection:setFixedLengthStreamingMode	(I)V
    //   66: aload_0
    //   67: ldc -116
    //   69: ldc -114
    //   71: invokevirtual 145	java/net/HttpURLConnection:setRequestProperty	(Ljava/lang/String;Ljava/lang/String;)V
    //   74: aload_2
    //   75: invokeinterface 151 1 0
    //   80: invokeinterface 157 1 0
    //   85: astore_2
    //   86: aload_2
    //   87: invokeinterface 162 1 0
    //   92: ifeq +70 -> 162
    //   95: aload_2
    //   96: invokeinterface 166 1 0
    //   101: checkcast 168	java/util/Map$Entry
    //   104: astore 4
    //   106: aload_0
    //   107: aload 4
    //   109: invokeinterface 171 1 0
    //   114: checkcast 34	java/lang/String
    //   117: aload 4
    //   119: invokeinterface 174 1 0
    //   124: checkcast 34	java/lang/String
    //   127: invokevirtual 145	java/net/HttpURLConnection:setRequestProperty	(Ljava/lang/String;Ljava/lang/String;)V
    //   130: goto -44 -> 86
    //   133: astore_2
    //   134: ldc -80
    //   136: iconst_1
    //   137: anewarray 4	java/lang/Object
    //   140: dup
    //   141: iconst_0
    //   142: aload_1
    //   143: aastore
    //   144: invokestatic 93	com/adobe/mobile/am:c	(Ljava/lang/String;[Ljava/lang/Object;)V
    //   147: invokestatic 181	com/adobe/mobile/af:a	()Lcom/adobe/mobile/af;
    //   150: invokevirtual 184	com/adobe/mobile/af:h	()Z
    //   153: ifne +7 -> 160
    //   156: aload_0
    //   157: invokevirtual 109	java/net/HttpURLConnection:disconnect	()V
    //   160: iconst_0
    //   161: ireturn
    //   162: new 186	java/io/BufferedOutputStream
    //   165: dup
    //   166: aload_0
    //   167: invokevirtual 190	java/net/HttpURLConnection:getOutputStream	()Ljava/io/OutputStream;
    //   170: invokespecial 193	java/io/BufferedOutputStream:<init>	(Ljava/io/OutputStream;)V
    //   173: astore_2
    //   174: aload_2
    //   175: aload_3
    //   176: invokevirtual 199	java/io/OutputStream:write	([B)V
    //   179: aload_2
    //   180: invokevirtual 200	java/io/OutputStream:close	()V
    //   183: aload_0
    //   184: invokevirtual 101	java/net/HttpURLConnection:getInputStream	()Ljava/io/InputStream;
    //   187: astore_2
    //   188: invokestatic 181	com/adobe/mobile/af:a	()Lcom/adobe/mobile/af;
    //   191: invokevirtual 184	com/adobe/mobile/af:h	()Z
    //   194: ifeq +48 -> 242
    //   197: bipush 10
    //   199: newarray <illegal type>
    //   201: astore_3
    //   202: aload_2
    //   203: aload_3
    //   204: invokevirtual 204	java/io/InputStream:read	([B)I
    //   207: ifgt -5 -> 202
    //   210: aload_2
    //   211: invokevirtual 106	java/io/InputStream:close	()V
    //   214: ldc -50
    //   216: iconst_1
    //   217: anewarray 4	java/lang/Object
    //   220: dup
    //   221: iconst_0
    //   222: aload_1
    //   223: aastore
    //   224: invokestatic 93	com/adobe/mobile/am:c	(Ljava/lang/String;[Ljava/lang/Object;)V
    //   227: invokestatic 181	com/adobe/mobile/af:a	()Lcom/adobe/mobile/af;
    //   230: invokevirtual 184	com/adobe/mobile/af:h	()Z
    //   233: ifne +7 -> 240
    //   236: aload_0
    //   237: invokevirtual 109	java/net/HttpURLConnection:disconnect	()V
    //   240: iconst_1
    //   241: ireturn
    //   242: aload_0
    //   243: invokevirtual 97	java/net/HttpURLConnection:getResponseCode	()I
    //   246: pop
    //   247: goto -37 -> 210
    //   250: astore_1
    //   251: ldc -48
    //   253: iconst_1
    //   254: anewarray 4	java/lang/Object
    //   257: dup
    //   258: iconst_0
    //   259: aload_1
    //   260: invokevirtual 116	java/io/IOException:getLocalizedMessage	()Ljava/lang/String;
    //   263: aastore
    //   264: invokestatic 93	com/adobe/mobile/am:c	(Ljava/lang/String;[Ljava/lang/Object;)V
    //   267: invokestatic 181	com/adobe/mobile/af:a	()Lcom/adobe/mobile/af;
    //   270: invokevirtual 184	com/adobe/mobile/af:h	()Z
    //   273: ifne +7 -> 280
    //   276: aload_0
    //   277: invokevirtual 109	java/net/HttpURLConnection:disconnect	()V
    //   280: iconst_0
    //   281: ireturn
    //   282: astore_1
    //   283: ldc -46
    //   285: iconst_1
    //   286: anewarray 4	java/lang/Object
    //   289: dup
    //   290: iconst_0
    //   291: aload_1
    //   292: invokevirtual 56	java/lang/Exception:getLocalizedMessage	()Ljava/lang/String;
    //   295: aastore
    //   296: invokestatic 61	com/adobe/mobile/am:a	(Ljava/lang/String;[Ljava/lang/Object;)V
    //   299: invokestatic 181	com/adobe/mobile/af:a	()Lcom/adobe/mobile/af;
    //   302: invokevirtual 184	com/adobe/mobile/af:h	()Z
    //   305: ifne -65 -> 240
    //   308: aload_0
    //   309: invokevirtual 109	java/net/HttpURLConnection:disconnect	()V
    //   312: goto -72 -> 240
    //   315: astore_1
    //   316: ldc -46
    //   318: iconst_1
    //   319: anewarray 4	java/lang/Object
    //   322: dup
    //   323: iconst_0
    //   324: aload_1
    //   325: invokevirtual 119	java/lang/Error:getLocalizedMessage	()Ljava/lang/String;
    //   328: aastore
    //   329: invokestatic 61	com/adobe/mobile/am:a	(Ljava/lang/String;[Ljava/lang/Object;)V
    //   332: invokestatic 181	com/adobe/mobile/af:a	()Lcom/adobe/mobile/af;
    //   335: invokevirtual 184	com/adobe/mobile/af:h	()Z
    //   338: ifne -98 -> 240
    //   341: aload_0
    //   342: invokevirtual 109	java/net/HttpURLConnection:disconnect	()V
    //   345: goto -105 -> 240
    //   348: astore_1
    //   349: invokestatic 181	com/adobe/mobile/af:a	()Lcom/adobe/mobile/af;
    //   352: invokevirtual 184	com/adobe/mobile/af:h	()Z
    //   355: ifne +7 -> 362
    //   358: aload_0
    //   359: invokevirtual 109	java/net/HttpURLConnection:disconnect	()V
    //   362: aload_1
    //   363: athrow
    // Local variable table:
    //   start	length	slot	name	signature
    //   0	364	0	paramString1	String
    //   0	364	1	paramString2	String
    //   0	364	2	paramMap	java.util.Map<String, String>
    //   59	145	3	arrayOfByte	byte[]
    //   104	14	4	localEntry	java.util.Map.Entry
    // Exception table:
    //   from	to	target	type
    //   33	86	133	java/net/SocketTimeoutException
    //   86	130	133	java/net/SocketTimeoutException
    //   162	202	133	java/net/SocketTimeoutException
    //   202	210	133	java/net/SocketTimeoutException
    //   210	227	133	java/net/SocketTimeoutException
    //   242	247	133	java/net/SocketTimeoutException
    //   33	86	250	java/io/IOException
    //   86	130	250	java/io/IOException
    //   162	202	250	java/io/IOException
    //   202	210	250	java/io/IOException
    //   210	227	250	java/io/IOException
    //   242	247	250	java/io/IOException
    //   33	86	282	java/lang/Exception
    //   86	130	282	java/lang/Exception
    //   162	202	282	java/lang/Exception
    //   202	210	282	java/lang/Exception
    //   210	227	282	java/lang/Exception
    //   242	247	282	java/lang/Exception
    //   33	86	315	java/lang/Error
    //   86	130	315	java/lang/Error
    //   162	202	315	java/lang/Error
    //   202	210	315	java/lang/Error
    //   210	227	315	java/lang/Error
    //   242	247	315	java/lang/Error
    //   33	86	348	finally
    //   86	130	348	finally
    //   134	147	348	finally
    //   162	202	348	finally
    //   202	210	348	finally
    //   210	227	348	finally
    //   242	247	348	finally
    //   251	267	348	finally
    //   283	299	348	finally
    //   316	332	348	finally
  }
  
  /* Error */
  protected static byte[] a(String paramString1, int paramInt, String paramString2)
  {
    // Byte code:
    //   0: aconst_null
    //   1: astore 7
    //   3: invokestatic 74	com/adobe/mobile/am:o	()Z
    //   6: ifeq +13 -> 19
    //   9: aload_0
    //   10: aconst_null
    //   11: iload_1
    //   12: aload_2
    //   13: invokestatic 215	com/adobe/mobile/ap:b	(Ljava/lang/String;Ljava/util/Map;ILjava/lang/String;)[B
    //   16: astore_3
    //   17: aload_3
    //   18: areturn
    //   19: aload_0
    //   20: invokestatic 81	com/adobe/mobile/al:a	(Ljava/lang/String;)Ljava/net/HttpURLConnection;
    //   23: astore_0
    //   24: aload_0
    //   25: sipush 2000
    //   28: invokevirtual 85	java/net/HttpURLConnection:setConnectTimeout	(I)V
    //   31: aload_0
    //   32: iload_1
    //   33: invokevirtual 88	java/net/HttpURLConnection:setReadTimeout	(I)V
    //   36: aload_0
    //   37: invokevirtual 97	java/net/HttpURLConnection:getResponseCode	()I
    //   40: sipush 200
    //   43: if_icmpne +221 -> 264
    //   46: aload_0
    //   47: invokevirtual 101	java/net/HttpURLConnection:getInputStream	()Ljava/io/InputStream;
    //   50: astore 5
    //   52: aload 5
    //   54: astore 4
    //   56: aload_0
    //   57: astore_3
    //   58: sipush 1024
    //   61: newarray <illegal type>
    //   63: astore 6
    //   65: aload 5
    //   67: astore 4
    //   69: aload_0
    //   70: astore_3
    //   71: new 217	java/io/ByteArrayOutputStream
    //   74: dup
    //   75: invokespecial 218	java/io/ByteArrayOutputStream:<init>	()V
    //   78: astore 8
    //   80: aload 5
    //   82: astore 4
    //   84: aload_0
    //   85: astore_3
    //   86: aload 5
    //   88: aload 6
    //   90: invokevirtual 204	java/io/InputStream:read	([B)I
    //   93: iconst_m1
    //   94: if_icmpeq +94 -> 188
    //   97: aload 5
    //   99: astore 4
    //   101: aload_0
    //   102: astore_3
    //   103: aload 8
    //   105: aload 6
    //   107: invokevirtual 219	java/io/ByteArrayOutputStream:write	([B)V
    //   110: goto -30 -> 80
    //   113: astore 6
    //   115: aload 5
    //   117: astore 4
    //   119: aload_0
    //   120: astore_3
    //   121: ldc -35
    //   123: iconst_2
    //   124: anewarray 4	java/lang/Object
    //   127: dup
    //   128: iconst_0
    //   129: aload_2
    //   130: aastore
    //   131: dup
    //   132: iconst_1
    //   133: aload 6
    //   135: invokevirtual 116	java/io/IOException:getLocalizedMessage	()Ljava/lang/String;
    //   138: aastore
    //   139: invokestatic 113	com/adobe/mobile/am:b	(Ljava/lang/String;[Ljava/lang/Object;)V
    //   142: aload_0
    //   143: ifnull +7 -> 150
    //   146: aload_0
    //   147: invokevirtual 109	java/net/HttpURLConnection:disconnect	()V
    //   150: aload 7
    //   152: astore_3
    //   153: aload 5
    //   155: ifnull -138 -> 17
    //   158: aload 5
    //   160: invokevirtual 106	java/io/InputStream:close	()V
    //   163: aconst_null
    //   164: areturn
    //   165: astore_0
    //   166: ldc -33
    //   168: iconst_2
    //   169: anewarray 4	java/lang/Object
    //   172: dup
    //   173: iconst_0
    //   174: aload_2
    //   175: aastore
    //   176: dup
    //   177: iconst_1
    //   178: aload_0
    //   179: invokevirtual 116	java/io/IOException:getLocalizedMessage	()Ljava/lang/String;
    //   182: aastore
    //   183: invokestatic 113	com/adobe/mobile/am:b	(Ljava/lang/String;[Ljava/lang/Object;)V
    //   186: aconst_null
    //   187: areturn
    //   188: aload 5
    //   190: astore 4
    //   192: aload_0
    //   193: astore_3
    //   194: aload 5
    //   196: invokevirtual 106	java/io/InputStream:close	()V
    //   199: aload 5
    //   201: astore 4
    //   203: aload_0
    //   204: astore_3
    //   205: aload 8
    //   207: invokevirtual 227	java/io/ByteArrayOutputStream:toByteArray	()[B
    //   210: astore 6
    //   212: aload 6
    //   214: astore 4
    //   216: aload_0
    //   217: ifnull +7 -> 224
    //   220: aload_0
    //   221: invokevirtual 109	java/net/HttpURLConnection:disconnect	()V
    //   224: aload 4
    //   226: astore_3
    //   227: aload 5
    //   229: ifnull -212 -> 17
    //   232: aload 5
    //   234: invokevirtual 106	java/io/InputStream:close	()V
    //   237: aload 4
    //   239: areturn
    //   240: astore_0
    //   241: ldc -33
    //   243: iconst_2
    //   244: anewarray 4	java/lang/Object
    //   247: dup
    //   248: iconst_0
    //   249: aload_2
    //   250: aastore
    //   251: dup
    //   252: iconst_1
    //   253: aload_0
    //   254: invokevirtual 116	java/io/IOException:getLocalizedMessage	()Ljava/lang/String;
    //   257: aastore
    //   258: invokestatic 113	com/adobe/mobile/am:b	(Ljava/lang/String;[Ljava/lang/Object;)V
    //   261: aload 4
    //   263: areturn
    //   264: aload 7
    //   266: astore_3
    //   267: aload_0
    //   268: ifnull -251 -> 17
    //   271: aload_0
    //   272: invokevirtual 109	java/net/HttpURLConnection:disconnect	()V
    //   275: aconst_null
    //   276: areturn
    //   277: astore 6
    //   279: aconst_null
    //   280: astore 5
    //   282: aconst_null
    //   283: astore_0
    //   284: aload 5
    //   286: astore 4
    //   288: aload_0
    //   289: astore_3
    //   290: ldc -27
    //   292: iconst_2
    //   293: anewarray 4	java/lang/Object
    //   296: dup
    //   297: iconst_0
    //   298: aload_2
    //   299: aastore
    //   300: dup
    //   301: iconst_1
    //   302: aload 6
    //   304: invokevirtual 56	java/lang/Exception:getLocalizedMessage	()Ljava/lang/String;
    //   307: aastore
    //   308: invokestatic 113	com/adobe/mobile/am:b	(Ljava/lang/String;[Ljava/lang/Object;)V
    //   311: aload_0
    //   312: ifnull +7 -> 319
    //   315: aload_0
    //   316: invokevirtual 109	java/net/HttpURLConnection:disconnect	()V
    //   319: aload 7
    //   321: astore_3
    //   322: aload 5
    //   324: ifnull -307 -> 17
    //   327: aload 5
    //   329: invokevirtual 106	java/io/InputStream:close	()V
    //   332: aconst_null
    //   333: areturn
    //   334: astore_0
    //   335: ldc -33
    //   337: iconst_2
    //   338: anewarray 4	java/lang/Object
    //   341: dup
    //   342: iconst_0
    //   343: aload_2
    //   344: aastore
    //   345: dup
    //   346: iconst_1
    //   347: aload_0
    //   348: invokevirtual 116	java/io/IOException:getLocalizedMessage	()Ljava/lang/String;
    //   351: aastore
    //   352: invokestatic 113	com/adobe/mobile/am:b	(Ljava/lang/String;[Ljava/lang/Object;)V
    //   355: aconst_null
    //   356: areturn
    //   357: astore 6
    //   359: aconst_null
    //   360: astore 5
    //   362: aconst_null
    //   363: astore_0
    //   364: aload 5
    //   366: astore 4
    //   368: aload_0
    //   369: astore_3
    //   370: ldc -25
    //   372: iconst_2
    //   373: anewarray 4	java/lang/Object
    //   376: dup
    //   377: iconst_0
    //   378: aload_2
    //   379: aastore
    //   380: dup
    //   381: iconst_1
    //   382: aload 6
    //   384: invokevirtual 119	java/lang/Error:getLocalizedMessage	()Ljava/lang/String;
    //   387: aastore
    //   388: invokestatic 113	com/adobe/mobile/am:b	(Ljava/lang/String;[Ljava/lang/Object;)V
    //   391: aload_0
    //   392: ifnull +7 -> 399
    //   395: aload_0
    //   396: invokevirtual 109	java/net/HttpURLConnection:disconnect	()V
    //   399: aload 7
    //   401: astore_3
    //   402: aload 5
    //   404: ifnull -387 -> 17
    //   407: aload 5
    //   409: invokevirtual 106	java/io/InputStream:close	()V
    //   412: aconst_null
    //   413: areturn
    //   414: astore_0
    //   415: ldc -33
    //   417: iconst_2
    //   418: anewarray 4	java/lang/Object
    //   421: dup
    //   422: iconst_0
    //   423: aload_2
    //   424: aastore
    //   425: dup
    //   426: iconst_1
    //   427: aload_0
    //   428: invokevirtual 116	java/io/IOException:getLocalizedMessage	()Ljava/lang/String;
    //   431: aastore
    //   432: invokestatic 113	com/adobe/mobile/am:b	(Ljava/lang/String;[Ljava/lang/Object;)V
    //   435: aconst_null
    //   436: areturn
    //   437: astore 5
    //   439: aconst_null
    //   440: astore 4
    //   442: aconst_null
    //   443: astore_0
    //   444: aload_0
    //   445: ifnull +7 -> 452
    //   448: aload_0
    //   449: invokevirtual 109	java/net/HttpURLConnection:disconnect	()V
    //   452: aload 4
    //   454: ifnull +8 -> 462
    //   457: aload 4
    //   459: invokevirtual 106	java/io/InputStream:close	()V
    //   462: aload 5
    //   464: athrow
    //   465: astore_0
    //   466: ldc -33
    //   468: iconst_2
    //   469: anewarray 4	java/lang/Object
    //   472: dup
    //   473: iconst_0
    //   474: aload_2
    //   475: aastore
    //   476: dup
    //   477: iconst_1
    //   478: aload_0
    //   479: invokevirtual 116	java/io/IOException:getLocalizedMessage	()Ljava/lang/String;
    //   482: aastore
    //   483: invokestatic 113	com/adobe/mobile/am:b	(Ljava/lang/String;[Ljava/lang/Object;)V
    //   486: goto -24 -> 462
    //   489: astore 5
    //   491: aconst_null
    //   492: astore 4
    //   494: goto -50 -> 444
    //   497: astore 5
    //   499: aload_3
    //   500: astore_0
    //   501: goto -57 -> 444
    //   504: astore 6
    //   506: aconst_null
    //   507: astore 5
    //   509: goto -145 -> 364
    //   512: astore 6
    //   514: goto -150 -> 364
    //   517: astore 6
    //   519: aconst_null
    //   520: astore 5
    //   522: goto -238 -> 284
    //   525: astore 6
    //   527: goto -243 -> 284
    //   530: astore 6
    //   532: aconst_null
    //   533: astore 5
    //   535: aconst_null
    //   536: astore_0
    //   537: goto -422 -> 115
    //   540: astore 6
    //   542: aconst_null
    //   543: astore 5
    //   545: goto -430 -> 115
    // Local variable table:
    //   start	length	slot	name	signature
    //   0	548	0	paramString1	String
    //   0	548	1	paramInt	int
    //   0	548	2	paramString2	String
    //   16	484	3	localObject1	Object
    //   54	439	4	localObject2	Object
    //   50	358	5	localInputStream	InputStream
    //   437	26	5	localObject3	Object
    //   489	1	5	localObject4	Object
    //   497	1	5	localObject5	Object
    //   507	37	5	localObject6	Object
    //   63	43	6	arrayOfByte1	byte[]
    //   113	21	6	localIOException1	IOException
    //   210	3	6	arrayOfByte2	byte[]
    //   277	26	6	localException1	Exception
    //   357	26	6	localError1	Error
    //   504	1	6	localError2	Error
    //   512	1	6	localError3	Error
    //   517	1	6	localException2	Exception
    //   525	1	6	localException3	Exception
    //   530	1	6	localIOException2	IOException
    //   540	1	6	localIOException3	IOException
    //   1	399	7	localObject7	Object
    //   78	128	8	localByteArrayOutputStream	java.io.ByteArrayOutputStream
    // Exception table:
    //   from	to	target	type
    //   58	65	113	java/io/IOException
    //   71	80	113	java/io/IOException
    //   86	97	113	java/io/IOException
    //   103	110	113	java/io/IOException
    //   194	199	113	java/io/IOException
    //   205	212	113	java/io/IOException
    //   158	163	165	java/io/IOException
    //   232	237	240	java/io/IOException
    //   19	24	277	java/lang/Exception
    //   327	332	334	java/io/IOException
    //   19	24	357	java/lang/Error
    //   407	412	414	java/io/IOException
    //   19	24	437	finally
    //   457	462	465	java/io/IOException
    //   24	52	489	finally
    //   58	65	497	finally
    //   71	80	497	finally
    //   86	97	497	finally
    //   103	110	497	finally
    //   121	142	497	finally
    //   194	199	497	finally
    //   205	212	497	finally
    //   290	311	497	finally
    //   370	391	497	finally
    //   24	52	504	java/lang/Error
    //   58	65	512	java/lang/Error
    //   71	80	512	java/lang/Error
    //   86	97	512	java/lang/Error
    //   103	110	512	java/lang/Error
    //   194	199	512	java/lang/Error
    //   205	212	512	java/lang/Error
    //   24	52	517	java/lang/Exception
    //   58	65	525	java/lang/Exception
    //   71	80	525	java/lang/Exception
    //   86	97	525	java/lang/Exception
    //   103	110	525	java/lang/Exception
    //   194	199	525	java/lang/Exception
    //   205	212	525	java/lang/Exception
    //   19	24	530	java/io/IOException
    //   24	52	540	java/io/IOException
  }
}

/* Location:
 * Qualified Name:     com.adobe.mobile.al
 * Java Class Version: 6 (50.0)
 * JD-Core Version:    0.7.1
 */